isincython/README.MD
isincython/__init__.py
isincython/requirements.txt
isincython/thirdparty.json
isincython-0.13.dist-info/LICENSE.rst
isincython-0.13.dist-info/METADATA
isincython-0.13.dist-info/WHEEL
isincython-0.13.dist-info/top_level.txt
isincython-0.13.dist-info/RECORD
