Metadata-Version: 2.1
Name: isincython
Version: 0.13
Summary: fast isin() function using Cython (C++) - up to 80 times faster than NumPy/Pandas.
Home-page: https://github.com/hansalemaos/isincython
Author: Johannes Fischer
Author-email: aulasparticularesdealemaosp@gmail.com
License: MIT
Keywords: isin,Cython
Classifier: Development Status :: 4 - Beta
Classifier: Programming Language :: Python :: 3 :: Only
Classifier: Programming Language :: Python :: 3.10
Classifier: Topic :: Software Development :: Libraries :: Python Modules
Classifier: Topic :: Utilities
License-File: LICENSE.rst
Requires-Dist: Cython
Requires-Dist: numpy
